onekit/__init__.py
onekit/dekit.py
onekit/exception.py
onekit/mathkit.py
onekit/numpykit.py
onekit/optfunckit.py
onekit/pandaskit.py
onekit/pythonkit.py
onekit/scipykit.py
onekit/sklearnkit.py
onekit/sparkkit.py
onekit/timekit.py
onekit/vizkit.py
onekit-5.0.0.dist-info/LICENSE
onekit-5.0.0.dist-info/METADATA
onekit-5.0.0.dist-info/WHEEL
onekit-5.0.0.dist-info/RECORD
