Metadata-Version: 2.3
Name: onekit
Version: 5.0.0
Summary: All-in-One Python Kit.
License: BSD 3-Clause
Keywords: onekit
Author: Eugen Stripling
Author-email: estripling042@gmail.com
Requires-Python: >=3.11
Classifier: Programming Language :: Python :: 3 :: Only
Classifier: Programming Language :: Python :: 3.11
Classifier: Programming Language :: Python :: 3.12
Provides-Extra: analytics
Provides-Extra: base
Provides-Extra: pyspark
Requires-Dist: duckdb (>=1.3.1,<2.0.0) ; extra == "base"
Requires-Dist: pandas[compression,computation,excel,output-formatting,parquet,performance,plot] (>=2.2.3,<3.0.0) ; extra == "analytics"
Requires-Dist: pyspark (==3.5.3) ; extra == "pyspark"
Requires-Dist: python-dateutil (>=2.9.0.post0,<3.0.0) ; extra == "base"
Requires-Dist: scikit-learn (>=1.6.1,<2.0.0) ; extra == "analytics"
Requires-Dist: toolz (>=1.0.0,<2.0.0) ; extra == "base"
Requires-Dist: tqdm (>=4.67.1,<5.0.0) ; extra == "analytics"
